{
  "lastUpdate": "12/05/2020 15:39",
  "vuelos": [
    {
      "tipo": "arribo",
      "aerolinea": "LA",
      "vuelo": "1130",
      "st": "12/05/2020 16:30",
      "matricula": "CCBGK",
      "posicion": "55",
      "et": "12/5/2020 15:50",
      "at": "",
      "term": "TCA",
      "sector": "",
      "cinta": "",
      "lF": "",
      "ruta": "MIA",
      "via": "",
      "remark": "EST",
      "sanidad": "NO",
      "pax": "0"
    },
    {
      "tipo": "arribo",
      "aerolinea": "M3",
      "vuelo": "8420",
      "st": "12/05/2020 17:00",
      "matricula": "",
      "posicion": "",
      "et": "",
      "at": "",
      "term": "TCA",
      "sector": "",
      "cinta": "",
      "lF": "",
      "ruta": "VCP",
      "via": "",
      "remark": "",
      "sanidad": "NO",
      "pax": ""
    },
    {
      "tipo": "arribo",
      "aerolinea": "AU",
      "vuelo": "2221",
      "st": "12/05/2020 18:10",
      "matricula": "LVCIH",
      "posicion": "12",
      "et": "12/5/2020 17:59",
      "at": "",
      "term": "A",
      "sector": "",
      "cinta": "9",
      "lF": "009",
      "ruta": "SSA",
      "via": "",
      "remark": "EST",
      "sanidad": "NO",
      "pax": "95"
    },
    {
      "tipo": "arribo",
      "aerolinea": "4M",
      "vuelo": "7963",
      "st": "12/05/2020 19:10",
      "matricula": "LVBFO",
      "posicion": "",
      "et": "",
      "at": "",
      "term": "A",
      "sector": "",
      "cinta": "",
      "lF": "",
      "ruta": "GRU",
      "via": "",
      "remark": "",
      "sanidad": "NO",
      "pax": ""
    },
    {
      "tipo": "arribo",
      "aerolinea": "4M",
      "vuelo": "7970",
      "st": "12/05/2020 20:40",
      "matricula": "LVBSJ",
      "posicion": "",
      "et": "",
      "at": "",
      "term": "C",
      "sector": "CAC",
      "cinta": "",
      "lF": "",
      "ruta": "MDZ",
      "via": "RGL",
      "remark": "",
      "sanidad": "NO",
      "pax": ""
    },
    {
      "tipo": "arribo",
      "aerolinea": "UC",
      "vuelo": "1401",
      "st": "12/05/2020 22:00",
      "matricula": "",
      "posicion": "",
      "et": "",
      "at": "",
      "term": "TCA",
      "sector": "",
      "cinta": "",
      "lF": "",
      "ruta": "MIA",
      "via": "",
      "remark": "",
      "sanidad": "NO",
      "pax": ""
    },
    {
      "tipo": "arribo",
      "aerolinea": "TK",
      "vuelo": "6169",
      "st": "12/05/2020 22:10",
      "matricula": "",
      "posicion": "",
      "et": "",
      "at": "",
      "term": "TCA",
      "sector": "",
      "cinta": "",
      "lF": "",
      "ruta": "IST",
      "via": "GRU",
      "remark": "",
      "sanidad": "NO",
      "pax": ""
    },
    {
      "tipo": "arribo",
      "aerolinea": "M3",
      "vuelo": "8492",
      "st": "12/05/2020 23:45",
      "matricula": "PRACO",
      "posicion": "",
      "et": "",
      "at": "",
      "term": "TCA",
      "sector": "",
      "cinta": "",
      "lF": "",
      "ruta": "VCP",
      "via": "",
      "remark": "",
      "sanidad": "NO",
      "pax": ""
    },
    {
      "tipo": "arribo",
      "aerolinea": "UC",
      "vuelo": "1403",
      "st": "13/05/2020 02:00",
      "matricula": "",
      "posicion": "",
      "et": "",
      "at": "",
      "term": "TCA",
      "sector": "",
      "cinta": "",
      "lF": "",
      "ruta": "MIA",
      "via": "",
      "remark": "",
      "sanidad": "NO",
      "pax": ""
    },
    {
      "tipo": "arribo",
      "aerolinea": "QR",
      "vuelo": "8155",
      "st": "13/05/2020 03:00",
      "matricula": "",
      "posicion": "",
      "et": "",
      "at": "",
      "term": "TCA",
      "sector": "",
      "cinta": "",
      "lF": "",
      "ruta": "DOH",
      "via": "GRU",
      "remark": "",
      "sanidad": "NO",
      "pax": ""
    },
    {
      "tipo": "arribo",
      "aerolinea": "LH",
      "vuelo": "8266",
      "st": "13/05/2020 03:35",
      "matricula": "",
      "posicion": "",
      "et": "",
      "at": "",
      "term": "TCA",
      "sector": "",
      "cinta": "",
      "lF": "",
      "ruta": "FRA",
      "via": "VCP",
      "remark": "",
      "sanidad": "NO",
      "pax": ""
    },
    {
      "tipo": "arribo",
      "aerolinea": "QR",
      "vuelo": "8157",
      "st": "12/05/2020 03:00",
      "matricula": "A7BFL",
      "posicion": "55",
      "et": "12/5/2020 05:24",
      "at": "12/5/2020 05:25",
      "term": "TCA",
      "sector": "",
      "cinta": "",
      "lF": "",
      "ruta": "DOH",
      "via": "GRU",
      "remark": "ATE",
      "sanidad": "NO",
      "pax": ""
    },
    {
      "tipo": "arribo",
      "aerolinea": "AOG",
      "vuelo": "101",
      "st": "12/05/2020 05:30",
      "matricula": "CXCAR",
      "posicion": "51A",
      "et": "",
      "at": "12/5/2020 05:43",
      "term": "TCA",
      "sector": "",
      "cinta": "",
      "lF": "",
      "ruta": "MVD",
      "via": "",
      "remark": "ATE",
      "sanidad": "NO",
      "pax": ""
    },
    {
      "tipo": "arribo",
      "aerolinea": "M3",
      "vuelo": "8491",
      "st": "12/05/2020 06:20",
      "matricula": "",
      "posicion": "",
      "et": "",
      "at": "",
      "term": "TCA",
      "sector": "",
      "cinta": "",
      "lF": "",
      "ruta": "SCL",
      "via": "",
      "remark": "CON",
      "sanidad": "NO",
      "pax": ""
    },
    {
      "tipo": "arribo",
      "aerolinea": "MP",
      "vuelo": "6912",
      "st": "12/05/2020 10:05",
      "matricula": "PHCKA",
      "posicion": "55",
      "et": "12/5/2020 09:30",
      "at": "12/5/2020 09:27",
      "term": "TCA",
      "sector": "",
      "cinta": "",
      "lF": "",
      "ruta": "AMS",
      "via": "VCP",
      "remark": "ATE",
      "sanidad": "NO",
      "pax": ""
    },
    {
      "tipo": "arribo",
      "aerolinea": "AOG",
      "vuelo": "102",
      "st": "12/05/2020 11:00",
      "matricula": "CXCAR",
      "posicion": "54A",
      "et": "",
      "at": "12/5/2020 11:09",
      "term": "TCA",
      "sector": "",
      "cinta": "",
      "lF": "",
      "ruta": "ASU",
      "via": "",
      "remark": "ATE",
      "sanidad": "NO",
      "pax": ""
    },
    {
      "tipo": "arribo",
      "aerolinea": "PRV",
      "vuelo": "VDJ",
      "st": "12/05/2020 11:00",
      "matricula": "LVVDJ",
      "posicion": "45",
      "et": "",
      "at": "12/5/2020 10:45",
      "term": "C",
      "sector": "CAC",
      "cinta": "",
      "lF": "",
      "ruta": "SLA",
      "via": "",
      "remark": "ATE",
      "sanidad": "NO",
      "pax": "13"
    },
    {
      "tipo": "arribo",
      "aerolinea": "PRV",
      "vuelo": "BGR",
      "st": "12/05/2020 10:00",
      "matricula": "LVBGR",
      "posicion": "44",
      "et": "12/5/2020 11:00",
      "at": "12/5/2020 10:53",
      "term": "C",
      "sector": "CAC",
      "cinta": "",
      "lF": "",
      "ruta": "POS",
      "via": "",
      "remark": "ATE",
      "sanidad": "NO",
      "pax": "9"
    },
    {
      "tipo": "arribo",
      "aerolinea": "PRV",
      "vuelo": "ZEB",
      "st": "12/05/2020 10:50",
      "matricula": "LVZEB",
      "posicion": "37",
      "et": "12/5/2020 11:15",
      "at": "12/5/2020 11:25",
      "term": "C",
      "sector": "CAC",
      "cinta": "",
      "lF": "",
      "ruta": "SLA",
      "via": "",
      "remark": "ATE",
      "sanidad": "NO",
      "pax": "0"
    },
    {
      "tipo": "arribo",
      "aerolinea": "AOG",
      "vuelo": "423",
      "st": "12/05/2020 11:20",
      "matricula": "CXCLS",
      "posicion": "57",
      "et": "",
      "at": "12/5/2020 11:29",
      "term": "TCA",
      "sector": "",
      "cinta": "",
      "lF": "",
      "ruta": "MVD",
      "via": "",
      "remark": "ATE",
      "sanidad": "NO",
      "pax": ""
    },
    {
      "tipo": "arribo",
      "aerolinea": "AOG",
      "vuelo": "501",
      "st": "12/05/2020 11:30",
      "matricula": "CXLSS",
      "posicion": "59",
      "et": "",
      "at": "12/5/2020 11:34",
      "term": "TCA",
      "sector": "",
      "cinta": "",
      "lF": "",
      "ruta": "ASU",
      "via": "",
      "remark": "ATE",
      "sanidad": "NO",
      "pax": ""
    },
    {
      "tipo": "arribo",
      "aerolinea": "AR",
      "vuelo": "1085",
      "st": "12/05/2020 11:40",
      "matricula": "LVGIF",
      "posicion": "50",
      "et": "",
      "at": "12/5/2020 10:34",
      "term": "TCA",
      "sector": "",
      "cinta": "",
      "lF": "",
      "ruta": "PVG",
      "via": "AKL",
      "remark": "ATE",
      "sanidad": "NO",
      "pax": ""
    },
    {
      "tipo": "arribo",
      "aerolinea": "NZ",
      "vuelo": "6196",
      "st": "12/05/2020 13:40",
      "matricula": "ZKOKP",
      "posicion": "11",
      "et": "12/5/2020 13:35",
      "at": "12/5/2020 13:35",
      "term": "TCA",
      "sector": "",
      "cinta": "",
      "lF": "",
      "ruta": "AKL",
      "via": "",
      "remark": "ATE",
      "sanidad": "NO",
      "pax": ""
    },
    {
      "tipo": "arribo",
      "aerolinea": "JJ",
      "vuelo": "9540",
      "st": "12/05/2020 15:00",
      "matricula": "PTXPH",
      "posicion": "08",
      "et": "12/5/2020 14:45",
      "at": "12/5/2020 14:38",
      "term": "A",
      "sector": "",
      "cinta": "",
      "lF": "",
      "ruta": "GRU",
      "via": "",
      "remark": "ATE",
      "sanidad": "NO",
      "pax": "0"
    },
    {
      "tipo": "partida",
      "aerolinea": "AOG",
      "vuelo": "103",
      "st": "12/05/2020 03:30",
      "matricula": "CXCAR",
      "posicion": "51A",
      "et": "",
      "at": "12/5/2020 03:42",
      "term": "TCA",
      "sector": "",
      "chkFrom": "",
      "chkTo": "",
      "puerta": "",
      "ruta": "MVD",
      "via": "",
      "remark": "PAR",
      "sanidad": "NO"
    },
    {
      "tipo": "partida",
      "aerolinea": "UC",
      "vuelo": "1101",
      "st": "12/05/2020 02:35",
      "matricula": "N534LA",
      "posicion": "56",
      "et": "12/5/2020 03:45",
      "at": "12/5/2020 03:39",
      "term": "TCA",
      "sector": "",
      "chkFrom": "",
      "chkTo": "",
      "puerta": "",
      "ruta": "SCL",
      "via": "",
      "remark": "PAR",
      "sanidad": "NO"
    },
    {
      "tipo": "partida",
      "aerolinea": "AOG",
      "vuelo": "101",
      "st": "12/05/2020 07:00",
      "matricula": "CXCAR",
      "posicion": "51A",
      "et": "",
      "at": "12/5/2020 07:11",
      "term": "TCA",
      "sector": "",
      "chkFrom": "",
      "chkTo": "",
      "puerta": "",
      "ruta": "ASU",
      "via": "",
      "remark": "PAR",
      "sanidad": "NO"
    },
    {
      "tipo": "partida",
      "aerolinea": "AU",
      "vuelo": "2220",
      "st": "12/05/2020 08:00",
      "matricula": "LVCIH",
      "posicion": "12",
      "et": "",
      "at": "12/5/2020 08:00",
      "term": "C",
      "sector": "CPI",
      "chkFrom": "221",
      "chkTo": "240",
      "puerta": "16",
      "ruta": "SSA",
      "via": "",
      "remark": "PAR",
      "sanidad": "NO"
    },
    {
      "tipo": "partida",
      "aerolinea": "QR",
      "vuelo": "8157",
      "st": "12/05/2020 04:45",
      "matricula": "A7BFL",
      "posicion": "55",
      "et": "12/5/2020 08:05",
      "at": "12/5/2020 08:17",
      "term": "TCA",
      "sector": "",
      "chkFrom": "",
      "chkTo": "",
      "puerta": "",
      "ruta": "DOH",
      "via": "UIO",
      "remark": "PAR",
      "sanidad": "NO"
    },
    {
      "tipo": "partida",
      "aerolinea": "M3",
      "vuelo": "8491",
      "st": "12/05/2020 09:30",
      "matricula": "",
      "posicion": "",
      "et": "",
      "at": "",
      "term": "TCA",
      "sector": "",
      "chkFrom": "",
      "chkTo": "",
      "puerta": "",
      "ruta": "VCP",
      "via": "",
      "remark": "CON",
      "sanidad": "NO"
    },
    {
      "tipo": "partida",
      "aerolinea": "4M",
      "vuelo": "7968",
      "st": "12/05/2020 10:25",
      "matricula": "LVBSJ",
      "posicion": "51A",
      "et": "",
      "at": "12/5/2020 11:15",
      "term": "A",
      "sector": "AP",
      "chkFrom": "041",
      "chkTo": "053",
      "puerta": "",
      "ruta": "MDZ",
      "via": "RGL",
      "remark": "PAR",
      "sanidad": "NO"
    },
    {
      "tipo": "partida",
      "aerolinea": "PRV",
      "vuelo": "BGR",
      "st": "12/05/2020 11:00",
      "matricula": "LVBGR",
      "posicion": "44",
      "et": "12/5/2020 12:15",
      "at": "12/5/2020 12:25",
      "term": "C",
      "sector": "CPC",
      "chkFrom": "",
      "chkTo": "",
      "puerta": "",
      "ruta": "FDO",
      "via": "",
      "remark": "PAR",
      "sanidad": "NO"
    },
    {
      "tipo": "partida",
      "aerolinea": "PRV",
      "vuelo": "VDJ",
      "st": "12/05/2020 12:00",
      "matricula": "LVVDJ",
      "posicion": "45",
      "et": "12/5/2020 12:15",
      "at": "12/5/2020 12:20",
      "term": "C",
      "sector": "CPC",
      "chkFrom": "",
      "chkTo": "",
      "puerta": "",
      "ruta": "FDO",
      "via": "",
      "remark": "PAR",
      "sanidad": "NO"
    },
    {
      "tipo": "partida",
      "aerolinea": "PRV",
      "vuelo": "ZEB",
      "st": "12/05/2020 11:50",
      "matricula": "LVZEB",
      "posicion": "37",
      "et": "12/5/2020 12:15",
      "at": "12/5/2020 12:48",
      "term": "C",
      "sector": "CPC",
      "chkFrom": "",
      "chkTo": "",
      "puerta": "",
      "ruta": "FDO",
      "via": "",
      "remark": "PAR",
      "sanidad": "NO"
    },
    {
      "tipo": "partida",
      "aerolinea": "AOG",
      "vuelo": "102",
      "st": "12/05/2020 12:30",
      "matricula": "CXCAR",
      "posicion": "54A",
      "et": "",
      "at": "12/5/2020 15:36",
      "term": "TCA",
      "sector": "",
      "chkFrom": "",
      "chkTo": "",
      "puerta": "",
      "ruta": "ASU",
      "via": "",
      "remark": "PAR",
      "sanidad": "NO"
    },
    {
      "tipo": "partida",
      "aerolinea": "MP",
      "vuelo": "6912",
      "st": "12/05/2020 12:05",
      "matricula": "PHCKA",
      "posicion": "55",
      "et": "12/5/2020 12:40",
      "at": "12/5/2020 12:35",
      "term": "TCA",
      "sector": "",
      "chkFrom": "",
      "chkTo": "",
      "puerta": "",
      "ruta": "AMS",
      "via": "UIO",
      "remark": "PAR",
      "sanidad": "NO"
    },
    {
      "tipo": "partida",
      "aerolinea": "4M",
      "vuelo": "7964",
      "st": "12/05/2020 12:00",
      "matricula": "LVBFO",
      "posicion": "02",
      "et": "12/5/2020 13:00",
      "at": "12/5/2020 14:20",
      "term": "A",
      "sector": "AP",
      "chkFrom": "041",
      "chkTo": "053",
      "puerta": "01",
      "ruta": "GRU",
      "via": "",
      "remark": "PAR",
      "sanidad": "NO"
    },
    {
      "tipo": "partida",
      "aerolinea": "AOG",
      "vuelo": "424",
      "st": "12/05/2020 13:00",
      "matricula": "CXCLS",
      "posicion": "57",
      "et": "",
      "at": "12/5/2020 13:09",
      "term": "TCA",
      "sector": "",
      "chkFrom": "",
      "chkTo": "",
      "puerta": "",
      "ruta": "MVD",
      "via": "",
      "remark": "PAR",
      "sanidad": "NO"
    },
    {
      "tipo": "partida",
      "aerolinea": "AOG",
      "vuelo": "500",
      "st": "12/05/2020 13:00",
      "matricula": "CXLSS",
      "posicion": "59",
      "et": "",
      "at": "12/5/2020 12:55",
      "term": "TCA",
      "sector": "",
      "chkFrom": "",
      "chkTo": "",
      "puerta": "",
      "ruta": "MVD",
      "via": "",
      "remark": "PAR",
      "sanidad": "NO"
    },
    {
      "tipo": "partida",
      "aerolinea": "JJ",
      "vuelo": "9453",
      "st": "12/05/2020 16:00",
      "matricula": "PTXPH",
      "posicion": "08",
      "et": "",
      "at": "",
      "term": "A",
      "sector": "AP",
      "chkFrom": "041",
      "chkTo": "053",
      "puerta": "07",
      "ruta": "GRU",
      "via": "",
      "remark": "BOR",
      "sanidad": "NO"
    },
    {
      "tipo": "partida",
      "aerolinea": "BA",
      "vuelo": "9129",
      "st": "12/05/2020 17:35",
      "matricula": "GZBKF",
      "posicion": "10",
      "et": "",
      "at": "",
      "term": "A",
      "sector": "AP",
      "chkFrom": "027",
      "chkTo": "032",
      "puerta": "10",
      "ruta": "LHR",
      "via": "",
      "remark": "HOR",
      "sanidad": "NO"
    },
    {
      "tipo": "partida",
      "aerolinea": "M3",
      "vuelo": "8420",
      "st": "12/05/2020 18:10",
      "matricula": "",
      "posicion": "",
      "et": "",
      "at": "",
      "term": "TCA",
      "sector": "",
      "chkFrom": "",
      "chkTo": "",
      "puerta": "",
      "ruta": "MIA",
      "via": "",
      "remark": "HOR",
      "sanidad": "NO"
    },
    {
      "tipo": "partida",
      "aerolinea": "LA",
      "vuelo": "1130",
      "st": "12/05/2020 18:30",
      "matricula": "CCBGK",
      "posicion": "55",
      "et": "",
      "at": "",
      "term": "TCA",
      "sector": "",
      "chkFrom": "",
      "chkTo": "",
      "puerta": "",
      "ruta": "SCL",
      "via": "",
      "remark": "HOR",
      "sanidad": "NO"
    },
    {
      "tipo": "partida",
      "aerolinea": "UC",
      "vuelo": "1402",
      "st": "12/05/2020 23:30",
      "matricula": "",
      "posicion": "",
      "et": "",
      "at": "",
      "term": "TCA",
      "sector": "",
      "chkFrom": "",
      "chkTo": "",
      "puerta": "",
      "ruta": "LAX",
      "via": "",
      "remark": "HOR",
      "sanidad": "NO"
    },
    {
      "tipo": "partida",
      "aerolinea": "AR",
      "vuelo": "1160",
      "st": "12/05/2020 23:50",
      "matricula": "LVGHQ",
      "posicion": "14",
      "et": "",
      "at": "",
      "term": "C",
      "sector": "CPI",
      "chkFrom": "221",
      "chkTo": "240",
      "puerta": "19",
      "ruta": "BCN",
      "via": "",
      "remark": "HOR",
      "sanidad": "NO"
    },
    {
      "tipo": "partida",
      "aerolinea": "AR",
      "vuelo": "H24",
      "st": "12/05/2020 23:59",
      "matricula": "",
      "posicion": "",
      "et": "",
      "at": "",
      "term": "C",
      "sector": "CPI",
      "chkFrom": "221",
      "chkTo": "240",
      "puerta": "",
      "ruta": "QTR",
      "via": "",
      "remark": "HOR",
      "sanidad": "NO"
    },
    {
      "tipo": "partida",
      "aerolinea": "AR",
      "vuelo": "H24N",
      "st": "12/05/2020 23:59",
      "matricula": "",
      "posicion": "",
      "et": "",
      "at": "",
      "term": "C",
      "sector": "CPI",
      "chkFrom": "209",
      "chkTo": "240",
      "puerta": "",
      "ruta": "QTR",
      "via": "",
      "remark": "HOR",
      "sanidad": "NO"
    },
    {
      "tipo": "partida",
      "aerolinea": "JJ",
      "vuelo": "H24",
      "st": "12/05/2020 23:59",
      "matricula": "",
      "posicion": "",
      "et": "",
      "at": "",
      "term": "A",
      "sector": "AP",
      "chkFrom": "041",
      "chkTo": "053",
      "puerta": "",
      "ruta": "QTR",
      "via": "",
      "remark": "HOR",
      "sanidad": "NO"
    },
    {
      "tipo": "partida",
      "aerolinea": "M3",
      "vuelo": "8492",
      "st": "13/05/2020 02:10",
      "matricula": "PRACO",
      "posicion": "",
      "et": "13/5/2020 01:07",
      "at": "",
      "term": "TCA",
      "sector": "",
      "chkFrom": "",
      "chkTo": "",
      "puerta": "",
      "ruta": "SCL",
      "via": "",
      "remark": "EST",
      "sanidad": "NO"
    },
    {
      "tipo": "partida",
      "aerolinea": "TK",
      "vuelo": "6170",
      "st": "13/05/2020 01:10",
      "matricula": "",
      "posicion": "",
      "et": "",
      "at": "",
      "term": "TCA",
      "sector": "",
      "chkFrom": "",
      "chkTo": "",
      "puerta": "",
      "ruta": "IST",
      "via": "GRU",
      "remark": "",
      "sanidad": "NO"
    },
    {
      "tipo": "partida",
      "aerolinea": "UC",
      "vuelo": "1404",
      "st": "13/05/2020 03:30",
      "matricula": "",
      "posicion": "",
      "et": "",
      "at": "",
      "term": "TCA",
      "sector": "",
      "chkFrom": "",
      "chkTo": "",
      "puerta": "",
      "ruta": "LAX",
      "via": "",
      "remark": "HOR",
      "sanidad": "NO"
    }
  ]
}