{
  "lastUpdate": "24/04/2020 21:27",
  "vuelos": [
    {
      "tipo": "arribo",
      "aerolinea": "UC",
      "vuelo": "1407",
      "st": "24/04/2020 22:00",
      "matricula": "",
      "posicion": "",
      "et": "",
      "at": "",
      "term": "TCA",
      "sector": "",
      "cinta": "",
      "lF": "",
      "ruta": "MIA",
      "via": "",
      "remark": "",
      "sanidad": "NO",
      "pax": ""
    },
    {
      "tipo": "arribo",
      "aerolinea": "PRV",
      "vuelo": "ZEB",
      "st": "24/04/2020 22:10",
      "matricula": "LVZEB",
      "posicion": "37",
      "et": "",
      "at": "",
      "term": "C",
      "sector": "CAC",
      "cinta": "",
      "lF": "",
      "ruta": "SLA",
      "via": "",
      "remark": "",
      "sanidad": "NO",
      "pax": "0"
    },
    {
      "tipo": "arribo",
      "aerolinea": "PRV",
      "vuelo": "VDJ",
      "st": "24/04/2020 22:20",
      "matricula": "LVVDJ",
      "posicion": "44",
      "et": "",
      "at": "",
      "term": "C",
      "sector": "CAC",
      "cinta": "",
      "lF": "",
      "ruta": "SLA",
      "via": "",
      "remark": "",
      "sanidad": "NO",
      "pax": "12"
    },
    {
      "tipo": "arribo",
      "aerolinea": "PRV",
      "vuelo": "BGR",
      "st": "24/04/2020 22:20",
      "matricula": "LVBGR",
      "posicion": "45",
      "et": "",
      "at": "",
      "term": "C",
      "sector": "CAC",
      "cinta": "",
      "lF": "",
      "ruta": "SLA",
      "via": "",
      "remark": "",
      "sanidad": "NO",
      "pax": "15"
    },
    {
      "tipo": "arribo",
      "aerolinea": "CM",
      "vuelo": "4005",
      "st": "24/04/2020 22:06",
      "matricula": "HP1715",
      "posicion": "",
      "et": "24/4/2020 22:24",
      "at": "",
      "term": "A",
      "sector": "",
      "cinta": "9",
      "lF": "009",
      "ruta": "PTY",
      "via": "",
      "remark": "DEM",
      "sanidad": "NO",
      "pax": "157"
    },
    {
      "tipo": "arribo",
      "aerolinea": "M3",
      "vuelo": "8496",
      "st": "24/04/2020 23:45",
      "matricula": "PRABD",
      "posicion": "54",
      "et": "24/4/2020 23:35",
      "at": "",
      "term": "TCA",
      "sector": "",
      "cinta": "",
      "lF": "",
      "ruta": "VCP",
      "via": "",
      "remark": "EST",
      "sanidad": "NO",
      "pax": ""
    },
    {
      "tipo": "arribo",
      "aerolinea": "LA",
      "vuelo": "1110",
      "st": "25/04/2020 01:50",
      "matricula": "CCBGL",
      "posicion": "",
      "et": "",
      "at": "",
      "term": "TCA",
      "sector": "",
      "cinta": "",
      "lF": "",
      "ruta": "SCL",
      "via": "",
      "remark": "",
      "sanidad": "NO",
      "pax": ""
    },
    {
      "tipo": "arribo",
      "aerolinea": "UC",
      "vuelo": "1405",
      "st": "25/04/2020 02:00",
      "matricula": "",
      "posicion": "",
      "et": "",
      "at": "",
      "term": "TCA",
      "sector": "",
      "cinta": "",
      "lF": "",
      "ruta": "MIA",
      "via": "",
      "remark": "",
      "sanidad": "NO",
      "pax": ""
    },
    {
      "tipo": "arribo",
      "aerolinea": "UC",
      "vuelo": "1105",
      "st": "25/04/2020 02:45",
      "matricula": "CCCZZ",
      "posicion": "",
      "et": "",
      "at": "",
      "term": "TCA",
      "sector": "",
      "cinta": "",
      "lF": "",
      "ruta": "MIA",
      "via": "",
      "remark": "",
      "sanidad": "NO",
      "pax": ""
    },
    {
      "tipo": "arribo",
      "aerolinea": "AA",
      "vuelo": "9434",
      "st": "25/04/2020 05:47",
      "matricula": "",
      "posicion": "",
      "et": "",
      "at": "",
      "term": "TCA",
      "sector": "",
      "cinta": "",
      "lF": "",
      "ruta": "MIA",
      "via": "",
      "remark": "",
      "sanidad": "NO",
      "pax": ""
    },
    {
      "tipo": "arribo",
      "aerolinea": "JJ",
      "vuelo": "9452",
      "st": "25/04/2020 09:00",
      "matricula": "PTXPN",
      "posicion": "",
      "et": "",
      "at": "",
      "term": "A",
      "sector": "",
      "cinta": "",
      "lF": "",
      "ruta": "GRU",
      "via": "",
      "remark": "",
      "sanidad": "NO",
      "pax": ""
    },
    {
      "tipo": "arribo",
      "aerolinea": "PRV",
      "vuelo": "BGH",
      "st": "24/04/2020 05:20",
      "matricula": "LVBGH",
      "posicion": "44",
      "et": "24/4/2020 10:10",
      "at": "24/4/2020 10:18",
      "term": "C",
      "sector": "CAC",
      "cinta": "",
      "lF": "",
      "ruta": "NQN",
      "via": "",
      "remark": "ATE",
      "sanidad": "NO",
      "pax": "11"
    },
    {
      "tipo": "arribo",
      "aerolinea": "PRV",
      "vuelo": "YIC",
      "st": "24/04/2020 05:20",
      "matricula": "LVYIC",
      "posicion": "45",
      "et": "24/4/2020 10:15",
      "at": "24/4/2020 10:25",
      "term": "C",
      "sector": "CAC",
      "cinta": "",
      "lF": "",
      "ruta": "NQN",
      "via": "",
      "remark": "ATE",
      "sanidad": "NO",
      "pax": "10"
    },
    {
      "tipo": "arribo",
      "aerolinea": "AOG",
      "vuelo": "423",
      "st": "24/04/2020 11:30",
      "matricula": "CXLSS",
      "posicion": "50A",
      "et": "",
      "at": "24/4/2020 10:51",
      "term": "TCA",
      "sector": "",
      "cinta": "",
      "lF": "",
      "ruta": "MVD",
      "via": "",
      "remark": "ATE",
      "sanidad": "NO",
      "pax": ""
    },
    {
      "tipo": "arribo",
      "aerolinea": "AOG",
      "vuelo": "501",
      "st": "24/04/2020 11:40",
      "matricula": "CXCLS",
      "posicion": "50B",
      "et": "",
      "at": "24/4/2020 11:24",
      "term": "TCA",
      "sector": "",
      "cinta": "",
      "lF": "",
      "ruta": "ASU",
      "via": "",
      "remark": "ATE",
      "sanidad": "NO",
      "pax": ""
    },
    {
      "tipo": "arribo",
      "aerolinea": "QF",
      "vuelo": "7027",
      "st": "24/04/2020 12:00",
      "matricula": "VHZNI",
      "posicion": "10",
      "et": "",
      "at": "24/4/2020 12:37",
      "term": "A",
      "sector": "",
      "cinta": "9",
      "lF": "009",
      "ruta": "MEL",
      "via": "",
      "remark": "ATE",
      "sanidad": "NO",
      "pax": "65"
    },
    {
      "tipo": "arribo",
      "aerolinea": "AV",
      "vuelo": "291",
      "st": "24/04/2020 13:36",
      "matricula": "N793AV",
      "posicion": "54",
      "et": "24/4/2020 12:40",
      "at": "24/4/2020 12:32",
      "term": "TCA",
      "sector": "",
      "cinta": "",
      "lF": "",
      "ruta": "BOG",
      "via": "",
      "remark": "ATE",
      "sanidad": "NO",
      "pax": "0"
    },
    {
      "tipo": "arribo",
      "aerolinea": "LA",
      "vuelo": "1147",
      "st": "24/04/2020 13:00",
      "matricula": "CCBGI",
      "posicion": "",
      "et": "",
      "at": "",
      "term": "TCA",
      "sector": "",
      "cinta": "",
      "lF": "",
      "ruta": "MIA",
      "via": "",
      "remark": "CON",
      "sanidad": "NO",
      "pax": ""
    },
    {
      "tipo": "arribo",
      "aerolinea": "M3",
      "vuelo": "8495",
      "st": "24/04/2020 14:00",
      "matricula": "",
      "posicion": "",
      "et": "",
      "at": "",
      "term": "TCA",
      "sector": "",
      "cinta": "",
      "lF": "",
      "ruta": "SCL",
      "via": "",
      "remark": "CON",
      "sanidad": "NO",
      "pax": ""
    },
    {
      "tipo": "arribo",
      "aerolinea": "M3",
      "vuelo": "8450",
      "st": "24/04/2020 14:00",
      "matricula": "",
      "posicion": "",
      "et": "",
      "at": "",
      "term": "TCA",
      "sector": "",
      "cinta": "",
      "lF": "",
      "ruta": "VCP",
      "via": "",
      "remark": "CON",
      "sanidad": "NO",
      "pax": ""
    },
    {
      "tipo": "arribo",
      "aerolinea": "UC",
      "vuelo": "1407",
      "st": "24/04/2020 15:11",
      "matricula": "N532LA",
      "posicion": "56",
      "et": "24/4/2020 14:57",
      "at": "24/4/2020 14:46",
      "term": "TCA",
      "sector": "",
      "cinta": "",
      "lF": "",
      "ruta": "SCL",
      "via": "",
      "remark": "ATE",
      "sanidad": "NO",
      "pax": ""
    },
    {
      "tipo": "arribo",
      "aerolinea": "UC",
      "vuelo": "1105",
      "st": "24/04/2020 17:00",
      "matricula": "CCCZZ",
      "posicion": "",
      "et": "",
      "at": "",
      "term": "TCA",
      "sector": "",
      "cinta": "",
      "lF": "",
      "ruta": "MIA",
      "via": "ASU",
      "remark": "CON",
      "sanidad": "NO",
      "pax": ""
    },
    {
      "tipo": "arribo",
      "aerolinea": "AZ",
      "vuelo": "8011",
      "st": "24/04/2020 17:05",
      "matricula": "EIISD",
      "posicion": "13",
      "et": "24/4/2020 17:50",
      "at": "24/4/2020 17:55",
      "term": "A",
      "sector": "",
      "cinta": "",
      "lF": "",
      "ruta": "FCO",
      "via": "",
      "remark": "ATE",
      "sanidad": "NO",
      "pax": "0"
    },
    {
      "tipo": "arribo",
      "aerolinea": "AOG",
      "vuelo": "502",
      "st": "24/04/2020 19:00",
      "matricula": "CXLSS",
      "posicion": "51A",
      "et": "",
      "at": "24/4/2020 19:02",
      "term": "TCA",
      "sector": "",
      "cinta": "",
      "lF": "",
      "ruta": "ASU",
      "via": "",
      "remark": "ATE",
      "sanidad": "NO",
      "pax": ""
    },
    {
      "tipo": "arribo",
      "aerolinea": "AOG",
      "vuelo": "421",
      "st": "24/04/2020 20:30",
      "matricula": "CXCLS",
      "posicion": "51A",
      "et": "",
      "at": "",
      "term": "TCA",
      "sector": "",
      "cinta": "",
      "lF": "",
      "ruta": "MVD",
      "via": "",
      "remark": "CON",
      "sanidad": "NO",
      "pax": ""
    },
    {
      "tipo": "arribo",
      "aerolinea": "LA",
      "vuelo": "1136",
      "st": "24/04/2020 21:20",
      "matricula": "CCBGE",
      "posicion": "55",
      "et": "24/4/2020 21:00",
      "at": "24/4/2020 21:07",
      "term": "TCA",
      "sector": "",
      "cinta": "",
      "lF": "",
      "ruta": "SCL",
      "via": "",
      "remark": "ATE",
      "sanidad": "NO",
      "pax": ""
    },
    {
      "tipo": "arribo",
      "aerolinea": "2D",
      "vuelo": "9303",
      "st": "24/04/2020 21:20",
      "matricula": "N700KW",
      "posicion": "08",
      "et": "",
      "at": "",
      "term": "A",
      "sector": "",
      "cinta": "",
      "lF": "",
      "ruta": "MIA",
      "via": "",
      "remark": "CON",
      "sanidad": "NO",
      "pax": ""
    },
    {
      "tipo": "partida",
      "aerolinea": "PRV",
      "vuelo": "YIC",
      "st": "24/04/2020 06:30",
      "matricula": "LVYIC",
      "posicion": "45",
      "et": "24/4/2020 11:00",
      "at": "24/4/2020 12:00",
      "term": "FBO",
      "sector": "",
      "chkFrom": "",
      "chkTo": "",
      "puerta": "",
      "ruta": "FDO",
      "via": "",
      "remark": "PAR",
      "sanidad": "NO"
    },
    {
      "tipo": "partida",
      "aerolinea": "PRV",
      "vuelo": "BGH",
      "st": "24/04/2020 06:30",
      "matricula": "LVBGH",
      "posicion": "44",
      "et": "24/4/2020 11:00",
      "at": "24/4/2020 12:01",
      "term": "FBO",
      "sector": "",
      "chkFrom": "",
      "chkTo": "",
      "puerta": "",
      "ruta": "FDO",
      "via": "",
      "remark": "PAR",
      "sanidad": "NO"
    },
    {
      "tipo": "partida",
      "aerolinea": "AOG",
      "vuelo": "424",
      "st": "24/04/2020 13:00",
      "matricula": "CXCLS",
      "posicion": "50B",
      "et": "",
      "at": "24/4/2020 12:05",
      "term": "TCA",
      "sector": "",
      "chkFrom": "",
      "chkTo": "",
      "puerta": "",
      "ruta": "MVD",
      "via": "",
      "remark": "PAR",
      "sanidad": "NO"
    },
    {
      "tipo": "partida",
      "aerolinea": "AOG",
      "vuelo": "500",
      "st": "24/04/2020 13:00",
      "matricula": "CXLSS",
      "posicion": "50A",
      "et": "",
      "at": "24/4/2020 11:48",
      "term": "TCA",
      "sector": "",
      "chkFrom": "",
      "chkTo": "",
      "puerta": "",
      "ruta": "ASU",
      "via": "",
      "remark": "PAR",
      "sanidad": "NO"
    },
    {
      "tipo": "partida",
      "aerolinea": "LA",
      "vuelo": "1147",
      "st": "24/04/2020 15:00",
      "matricula": "CCBGI",
      "posicion": "",
      "et": "",
      "at": "",
      "term": "TCA",
      "sector": "",
      "chkFrom": "",
      "chkTo": "",
      "puerta": "",
      "ruta": "SCL",
      "via": "",
      "remark": "CON",
      "sanidad": "NO"
    },
    {
      "tipo": "partida",
      "aerolinea": "M3",
      "vuelo": "8450",
      "st": "24/04/2020 15:10",
      "matricula": "",
      "posicion": "",
      "et": "",
      "at": "",
      "term": "TCA",
      "sector": "",
      "chkFrom": "",
      "chkTo": "",
      "puerta": "",
      "ruta": "MIA",
      "via": "",
      "remark": "CON",
      "sanidad": "NO"
    },
    {
      "tipo": "partida",
      "aerolinea": "M3",
      "vuelo": "8495",
      "st": "24/04/2020 15:10",
      "matricula": "",
      "posicion": "",
      "et": "",
      "at": "",
      "term": "TCA",
      "sector": "",
      "chkFrom": "",
      "chkTo": "",
      "puerta": "",
      "ruta": "VCP",
      "via": "",
      "remark": "CON",
      "sanidad": "NO"
    },
    {
      "tipo": "partida",
      "aerolinea": "UC",
      "vuelo": "1408",
      "st": "24/04/2020 16:30",
      "matricula": "N532LA",
      "posicion": "56",
      "et": "",
      "at": "24/4/2020 16:23",
      "term": "TCA",
      "sector": "",
      "chkFrom": "",
      "chkTo": "",
      "puerta": "",
      "ruta": "MIA",
      "via": "",
      "remark": "PAR",
      "sanidad": "NO"
    },
    {
      "tipo": "partida",
      "aerolinea": "AV",
      "vuelo": "290",
      "st": "24/04/2020 17:36",
      "matricula": "N793AV",
      "posicion": "54",
      "et": "",
      "at": "24/4/2020 16:07",
      "term": "TCA",
      "sector": "",
      "chkFrom": "",
      "chkTo": "",
      "puerta": "",
      "ruta": "BOG",
      "via": "",
      "remark": "PAR",
      "sanidad": "NO"
    },
    {
      "tipo": "partida",
      "aerolinea": "AOG",
      "vuelo": "426",
      "st": "24/04/2020 20:00",
      "matricula": "CXLSS",
      "posicion": "51A",
      "et": "",
      "at": "24/4/2020 20:25",
      "term": "TCA",
      "sector": "",
      "chkFrom": "",
      "chkTo": "",
      "puerta": "",
      "ruta": "MVD",
      "via": "",
      "remark": "PAR",
      "sanidad": "NO"
    },
    {
      "tipo": "partida",
      "aerolinea": "UC",
      "vuelo": "1105",
      "st": "24/04/2020 18:10",
      "matricula": "CCCZZ",
      "posicion": "",
      "et": "25/4/2020 02:45",
      "at": "",
      "term": "TCA",
      "sector": "",
      "chkFrom": "",
      "chkTo": "",
      "puerta": "",
      "ruta": "SCL",
      "via": "",
      "remark": "DEM",
      "sanidad": "NO"
    },
    {
      "tipo": "partida",
      "aerolinea": "M3",
      "vuelo": "8496",
      "st": "25/04/2020 02:10",
      "matricula": "PRABD",
      "posicion": "54",
      "et": "25/4/2020 01:00",
      "at": "",
      "term": "TCA",
      "sector": "",
      "chkFrom": "",
      "chkTo": "",
      "puerta": "",
      "ruta": "SCL",
      "via": "",
      "remark": "EST",
      "sanidad": "NO"
    },
    {
      "tipo": "partida",
      "aerolinea": "AOG",
      "vuelo": "526",
      "st": "24/04/2020 22:00",
      "matricula": "CXCLS",
      "posicion": "51A",
      "et": "",
      "at": "",
      "term": "TCA",
      "sector": "",
      "chkFrom": "",
      "chkTo": "",
      "puerta": "",
      "ruta": "MVD",
      "via": "",
      "remark": "HOR",
      "sanidad": "NO"
    },
    {
      "tipo": "partida",
      "aerolinea": "LA",
      "vuelo": "1136",
      "st": "24/04/2020 22:55",
      "matricula": "CCBGE",
      "posicion": "55",
      "et": "",
      "at": "",
      "term": "TCA",
      "sector": "",
      "chkFrom": "",
      "chkTo": "",
      "puerta": "",
      "ruta": "MIA",
      "via": "",
      "remark": "HOR",
      "sanidad": "NO"
    },
    {
      "tipo": "partida",
      "aerolinea": "PRV",
      "vuelo": "ZEB",
      "st": "24/04/2020 23:00",
      "matricula": "LVZEB",
      "posicion": "45",
      "et": "",
      "at": "",
      "term": "FBO",
      "sector": "",
      "chkFrom": "",
      "chkTo": "",
      "puerta": "",
      "ruta": "COR",
      "via": "",
      "remark": "HOR",
      "sanidad": "NO"
    },
    {
      "tipo": "partida",
      "aerolinea": "PRV",
      "vuelo": "BGR",
      "st": "24/04/2020 23:20",
      "matricula": "LVBGR",
      "posicion": "",
      "et": "",
      "at": "",
      "term": "FBO",
      "sector": "",
      "chkFrom": "",
      "chkTo": "",
      "puerta": "",
      "ruta": "FDO",
      "via": "",
      "remark": "HOR",
      "sanidad": "NO"
    },
    {
      "tipo": "partida",
      "aerolinea": "PRV",
      "vuelo": "VDJ",
      "st": "24/04/2020 23:20",
      "matricula": "LVVDJ",
      "posicion": "44",
      "et": "",
      "at": "",
      "term": "FBO",
      "sector": "",
      "chkFrom": "",
      "chkTo": "",
      "puerta": "",
      "ruta": "COR",
      "via": "",
      "remark": "HOR",
      "sanidad": "NO"
    },
    {
      "tipo": "partida",
      "aerolinea": "UC",
      "vuelo": "1408",
      "st": "24/04/2020 23:30",
      "matricula": "",
      "posicion": "",
      "et": "",
      "at": "",
      "term": "TCA",
      "sector": "",
      "chkFrom": "",
      "chkTo": "",
      "puerta": "",
      "ruta": "LAX",
      "via": "",
      "remark": "HOR",
      "sanidad": "NO"
    },
    {
      "tipo": "partida",
      "aerolinea": "JJ",
      "vuelo": "H24",
      "st": "24/04/2020 23:59",
      "matricula": "",
      "posicion": "",
      "et": "",
      "at": "",
      "term": "A",
      "sector": "AP",
      "chkFrom": "041",
      "chkTo": "053",
      "puerta": "",
      "ruta": "QTR",
      "via": "",
      "remark": "HOR",
      "sanidad": "NO"
    },
    {
      "tipo": "partida",
      "aerolinea": "AR",
      "vuelo": "H24N",
      "st": "24/04/2020 23:59",
      "matricula": "",
      "posicion": "",
      "et": "",
      "at": "",
      "term": "C",
      "sector": "CPI",
      "chkFrom": "209",
      "chkTo": "240",
      "puerta": "",
      "ruta": "QTR",
      "via": "",
      "remark": "HOR",
      "sanidad": "NO"
    },
    {
      "tipo": "partida",
      "aerolinea": "AR",
      "vuelo": "H24",
      "st": "24/04/2020 23:59",
      "matricula": "",
      "posicion": "",
      "et": "",
      "at": "",
      "term": "C",
      "sector": "CPI",
      "chkFrom": "221",
      "chkTo": "240",
      "puerta": "",
      "ruta": "QTR",
      "via": "",
      "remark": "HOR",
      "sanidad": "NO"
    },
    {
      "tipo": "partida",
      "aerolinea": "UC",
      "vuelo": "1406",
      "st": "25/04/2020 03:30",
      "matricula": "",
      "posicion": "",
      "et": "",
      "at": "",
      "term": "TCA",
      "sector": "",
      "chkFrom": "",
      "chkTo": "",
      "puerta": "",
      "ruta": "LAX",
      "via": "",
      "remark": "HOR",
      "sanidad": "NO"
    },
    {
      "tipo": "partida",
      "aerolinea": "UC",
      "vuelo": "1105",
      "st": "25/04/2020 03:55",
      "matricula": "CCCZZ",
      "posicion": "",
      "et": "",
      "at": "",
      "term": "TCA",
      "sector": "",
      "chkFrom": "",
      "chkTo": "",
      "puerta": "",
      "ruta": "SCL",
      "via": "",
      "remark": "HOR",
      "sanidad": "NO"
    },
    {
      "tipo": "partida",
      "aerolinea": "LA",
      "vuelo": "1110",
      "st": "25/04/2020 04:00",
      "matricula": "CCBGL",
      "posicion": "",
      "et": "",
      "at": "",
      "term": "TCA",
      "sector": "",
      "chkFrom": "",
      "chkTo": "",
      "puerta": "",
      "ruta": "MIA",
      "via": "",
      "remark": "HOR",
      "sanidad": "NO"
    },
    {
      "tipo": "partida",
      "aerolinea": "5X",
      "vuelo": "413",
      "st": "25/04/2020 06:05",
      "matricula": "N355UP",
      "posicion": "61",
      "et": "",
      "at": "",
      "term": "TCA",
      "sector": "",
      "chkFrom": "",
      "chkTo": "",
      "puerta": "",
      "ruta": "MIA",
      "via": "VCP",
      "remark": "HOR",
      "sanidad": "NO"
    },
    {
      "tipo": "partida",
      "aerolinea": "AA",
      "vuelo": "9435",
      "st": "25/04/2020 07:00",
      "matricula": "",
      "posicion": "",
      "et": "",
      "at": "",
      "term": "TCA",
      "sector": "",
      "chkFrom": "",
      "chkTo": "",
      "puerta": "",
      "ruta": "MIA",
      "via": "",
      "remark": "HOR",
      "sanidad": "NO"
    },
    {
      "tipo": "partida",
      "aerolinea": "4M",
      "vuelo": "7964",
      "st": "25/04/2020 07:00",
      "matricula": "LVBFO",
      "posicion": "",
      "et": "",
      "at": "",
      "term": "A",
      "sector": "AP",
      "chkFrom": "041",
      "chkTo": "053",
      "puerta": "",
      "ruta": "SCL",
      "via": "",
      "remark": "",
      "sanidad": "NO"
    },
    {
      "tipo": "partida",
      "aerolinea": "JJ",
      "vuelo": "9453",
      "st": "25/04/2020 09:00",
      "matricula": "PTXPN",
      "posicion": "",
      "et": "",
      "at": "",
      "term": "A",
      "sector": "AP",
      "chkFrom": "041",
      "chkTo": "053",
      "puerta": "",
      "ruta": "GRU",
      "via": "",
      "remark": "HOR",
      "sanidad": "NO"
    }
  ]
}