{
  "lastUpdate": "17/04/2020 20:38",
  "vuelos": [
    {
      "tipo": "arribo",
      "aerolinea": "AOG",
      "vuelo": "421",
      "st": "17/04/2020 21:00",
      "matricula": "CXLSS",
      "posicion": "56B",
      "et": "",
      "at": "",
      "term": "TCA",
      "sector": "",
      "cinta": "",
      "lF": "",
      "ruta": "MVD",
      "via": "",
      "remark": "",
      "sanidad": "NO",
      "pax": ""
    },
    {
      "tipo": "arribo",
      "aerolinea": "LA",
      "vuelo": "1148",
      "st": "17/04/2020 21:50",
      "matricula": "CCBGI",
      "posicion": "",
      "et": "17/4/2020 21:40",
      "at": "",
      "term": "TCA",
      "sector": "",
      "cinta": "",
      "lF": "",
      "ruta": "SCL",
      "via": "",
      "remark": "EST",
      "sanidad": "NO",
      "pax": "0"
    },
    {
      "tipo": "arribo",
      "aerolinea": "UC",
      "vuelo": "1407",
      "st": "17/04/2020 22:00",
      "matricula": "",
      "posicion": "",
      "et": "",
      "at": "",
      "term": "TCA",
      "sector": "",
      "cinta": "",
      "lF": "",
      "ruta": "MIA",
      "via": "",
      "remark": "",
      "sanidad": "NO",
      "pax": ""
    },
    {
      "tipo": "arribo",
      "aerolinea": "M3",
      "vuelo": "8496",
      "st": "17/04/2020 23:45",
      "matricula": "",
      "posicion": "",
      "et": "",
      "at": "",
      "term": "TCA",
      "sector": "",
      "cinta": "",
      "lF": "",
      "ruta": "VCP",
      "via": "",
      "remark": "",
      "sanidad": "NO",
      "pax": ""
    },
    {
      "tipo": "arribo",
      "aerolinea": "UC",
      "vuelo": "1405",
      "st": "18/04/2020 02:00",
      "matricula": "",
      "posicion": "",
      "et": "",
      "at": "",
      "term": "TCA",
      "sector": "",
      "cinta": "",
      "lF": "",
      "ruta": "MIA",
      "via": "",
      "remark": "",
      "sanidad": "NO",
      "pax": ""
    },
    {
      "tipo": "arribo",
      "aerolinea": "AR",
      "vuelo": "1071",
      "st": "18/04/2020 05:15",
      "matricula": "",
      "posicion": "",
      "et": "",
      "at": "",
      "term": "TCA",
      "sector": "",
      "cinta": "",
      "lF": "",
      "ruta": "PVG",
      "via": "AKL",
      "remark": "",
      "sanidad": "NO",
      "pax": ""
    },
    {
      "tipo": "arribo",
      "aerolinea": "AA",
      "vuelo": "9434",
      "st": "17/04/2020 08:42",
      "matricula": "N797AN",
      "posicion": "50",
      "et": "17/4/2020 11:20",
      "at": "17/4/2020 11:23",
      "term": "TCA",
      "sector": "",
      "cinta": "",
      "lF": "",
      "ruta": "MIA",
      "via": "",
      "remark": "ATE",
      "sanidad": "NO",
      "pax": ""
    },
    {
      "tipo": "arribo",
      "aerolinea": "AOG",
      "vuelo": "423",
      "st": "17/04/2020 11:30",
      "matricula": "CXLSS",
      "posicion": "56B",
      "et": "",
      "at": "17/4/2020 11:41",
      "term": "TCA",
      "sector": "",
      "cinta": "",
      "lF": "",
      "ruta": "MVD",
      "via": "",
      "remark": "ATE",
      "sanidad": "NO",
      "pax": ""
    },
    {
      "tipo": "arribo",
      "aerolinea": "AOG",
      "vuelo": "501",
      "st": "17/04/2020 11:30",
      "matricula": "CXCLS",
      "posicion": "54A",
      "et": "",
      "at": "17/4/2020 11:30",
      "term": "TCA",
      "sector": "",
      "cinta": "",
      "lF": "",
      "ruta": "ASU",
      "via": "",
      "remark": "ATE",
      "sanidad": "NO",
      "pax": ""
    },
    {
      "tipo": "arribo",
      "aerolinea": "M3",
      "vuelo": "8450",
      "st": "17/04/2020 14:00",
      "matricula": "",
      "posicion": "",
      "et": "",
      "at": "",
      "term": "TCA",
      "sector": "",
      "cinta": "",
      "lF": "",
      "ruta": "VCP",
      "via": "",
      "remark": "CON",
      "sanidad": "NO",
      "pax": ""
    },
    {
      "tipo": "arribo",
      "aerolinea": "M3",
      "vuelo": "8495",
      "st": "17/04/2020 14:00",
      "matricula": "",
      "posicion": "",
      "et": "",
      "at": "",
      "term": "TCA",
      "sector": "",
      "cinta": "",
      "lF": "",
      "ruta": "SCL",
      "via": "",
      "remark": "CON",
      "sanidad": "NO",
      "pax": ""
    },
    {
      "tipo": "arribo",
      "aerolinea": "LA",
      "vuelo": "1145",
      "st": "17/04/2020 14:40",
      "matricula": "CCBGB",
      "posicion": "10",
      "et": "17/4/2020 14:40",
      "at": "17/4/2020 14:44",
      "term": "A",
      "sector": "",
      "cinta": "8",
      "lF": "008",
      "ruta": "SYD",
      "via": "",
      "remark": "ATE",
      "sanidad": "NO",
      "pax": "288"
    },
    {
      "tipo": "arribo",
      "aerolinea": "UC",
      "vuelo": "1105",
      "st": "17/04/2020 17:00",
      "matricula": "",
      "posicion": "",
      "et": "",
      "at": "",
      "term": "TCA",
      "sector": "",
      "cinta": "",
      "lF": "",
      "ruta": "MIA",
      "via": "",
      "remark": "CON",
      "sanidad": "NO",
      "pax": ""
    },
    {
      "tipo": "arribo",
      "aerolinea": "PRV",
      "vuelo": "GVT",
      "st": "17/04/2020 18:30",
      "matricula": "LVGVT",
      "posicion": "41",
      "et": "",
      "at": "17/4/2020 17:42",
      "term": "FBO",
      "sector": "",
      "cinta": "",
      "lF": "",
      "ruta": "CPC",
      "via": "",
      "remark": "ATE",
      "sanidad": "NO",
      "pax": "2"
    },
    {
      "tipo": "arribo",
      "aerolinea": "AOG",
      "vuelo": "502",
      "st": "17/04/2020 19:00",
      "matricula": "CXCLS",
      "posicion": "56B",
      "et": "17/4/2020 19:20",
      "at": "17/4/2020 19:08",
      "term": "TCA",
      "sector": "",
      "cinta": "",
      "lF": "",
      "ruta": "ASU",
      "via": "",
      "remark": "ATE",
      "sanidad": "NO",
      "pax": ""
    },
    {
      "tipo": "arribo",
      "aerolinea": "2D",
      "vuelo": "9303",
      "st": "17/04/2020 21:20",
      "matricula": "N703KW",
      "posicion": "11",
      "et": "17/4/2020 19:30",
      "at": "17/4/2020 19:31",
      "term": "A",
      "sector": "",
      "cinta": "",
      "lF": "",
      "ruta": "MIA",
      "via": "",
      "remark": "ATE",
      "sanidad": "NO",
      "pax": ""
    },
    {
      "tipo": "partida",
      "aerolinea": "AA",
      "vuelo": "9437",
      "st": "17/04/2020 09:20",
      "matricula": "N724AN",
      "posicion": "50",
      "et": "",
      "at": "17/4/2020 09:20",
      "term": "TCA",
      "sector": "",
      "chkFrom": "",
      "chkTo": "",
      "puerta": "",
      "ruta": "DFW",
      "via": "",
      "remark": "PAR",
      "sanidad": "NO"
    },
    {
      "tipo": "partida",
      "aerolinea": "AOG",
      "vuelo": "424",
      "st": "17/04/2020 12:30",
      "matricula": "CXLSS",
      "posicion": "56B",
      "et": "",
      "at": "17/4/2020 12:34",
      "term": "TCA",
      "sector": "",
      "chkFrom": "",
      "chkTo": "",
      "puerta": "",
      "ruta": "MVD",
      "via": "",
      "remark": "PAR",
      "sanidad": "NO"
    },
    {
      "tipo": "partida",
      "aerolinea": "AOG",
      "vuelo": "500",
      "st": "17/04/2020 12:30",
      "matricula": "CXCLS",
      "posicion": "54A",
      "et": "",
      "at": "17/4/2020 12:25",
      "term": "TCA",
      "sector": "",
      "chkFrom": "",
      "chkTo": "",
      "puerta": "",
      "ruta": "ASU",
      "via": "",
      "remark": "PAR",
      "sanidad": "NO"
    },
    {
      "tipo": "partida",
      "aerolinea": "M3",
      "vuelo": "8495",
      "st": "17/04/2020 15:10",
      "matricula": "",
      "posicion": "",
      "et": "",
      "at": "",
      "term": "TCA",
      "sector": "",
      "chkFrom": "",
      "chkTo": "",
      "puerta": "",
      "ruta": "VCP",
      "via": "",
      "remark": "CON",
      "sanidad": "NO"
    },
    {
      "tipo": "partida",
      "aerolinea": "M3",
      "vuelo": "8450",
      "st": "17/04/2020 15:10",
      "matricula": "",
      "posicion": "",
      "et": "",
      "at": "",
      "term": "TCA",
      "sector": "",
      "chkFrom": "",
      "chkTo": "",
      "puerta": "",
      "ruta": "MIA",
      "via": "",
      "remark": "CON",
      "sanidad": "NO"
    },
    {
      "tipo": "partida",
      "aerolinea": "UC",
      "vuelo": "1105",
      "st": "17/04/2020 18:10",
      "matricula": "",
      "posicion": "",
      "et": "",
      "at": "",
      "term": "TCA",
      "sector": "",
      "chkFrom": "",
      "chkTo": "",
      "puerta": "",
      "ruta": "SCL",
      "via": "",
      "remark": "CON",
      "sanidad": "NO"
    },
    {
      "tipo": "partida",
      "aerolinea": "AR",
      "vuelo": "1070",
      "st": "17/04/2020 18:30",
      "matricula": "LVFVH",
      "posicion": "12",
      "et": "",
      "at": "17/4/2020 18:37",
      "term": "TCA",
      "sector": "",
      "chkFrom": "",
      "chkTo": "",
      "puerta": "16",
      "ruta": "PVG",
      "via": "AKL",
      "remark": "PAR",
      "sanidad": "NO"
    },
    {
      "tipo": "partida",
      "aerolinea": "PRV",
      "vuelo": "GVT",
      "st": "17/04/2020 19:00",
      "matricula": "LVGVT",
      "posicion": "41",
      "et": "",
      "at": "17/4/2020 18:25",
      "term": "FBO",
      "sector": "",
      "chkFrom": "",
      "chkTo": "",
      "puerta": "",
      "ruta": "FDO",
      "via": "",
      "remark": "PAR",
      "sanidad": "NO"
    },
    {
      "tipo": "partida",
      "aerolinea": "AOG",
      "vuelo": "426",
      "st": "17/04/2020 20:00",
      "matricula": "CXCLS",
      "posicion": "56B",
      "et": "",
      "at": "17/4/2020 19:46",
      "term": "TCA",
      "sector": "",
      "chkFrom": "",
      "chkTo": "",
      "puerta": "",
      "ruta": "MVD",
      "via": "",
      "remark": "PAR",
      "sanidad": "NO"
    },
    {
      "tipo": "partida",
      "aerolinea": "LH",
      "vuelo": "345",
      "st": "17/04/2020 20:30",
      "matricula": "DABVR",
      "posicion": "09",
      "et": "",
      "at": "",
      "term": "A",
      "sector": "AP",
      "chkFrom": "027",
      "chkTo": "040",
      "puerta": "08",
      "ruta": "FRA",
      "via": "",
      "remark": "CER",
      "sanidad": "NO"
    },
    {
      "tipo": "partida",
      "aerolinea": "LA",
      "vuelo": "1146",
      "st": "17/04/2020 17:20",
      "matricula": "CCBGB",
      "posicion": "10",
      "et": "17/4/2020 18:20",
      "at": "",
      "term": "A",
      "sector": "AP",
      "chkFrom": "041",
      "chkTo": "053",
      "puerta": "10",
      "ruta": "SCL",
      "via": "",
      "remark": "DEM",
      "sanidad": "NO"
    },
    {
      "tipo": "partida",
      "aerolinea": "AOG",
      "vuelo": "526",
      "st": "17/04/2020 22:00",
      "matricula": "CXLSS",
      "posicion": "56B",
      "et": "",
      "at": "",
      "term": "TCA",
      "sector": "",
      "chkFrom": "",
      "chkTo": "",
      "puerta": "",
      "ruta": "MVD",
      "via": "",
      "remark": "HOR",
      "sanidad": "NO"
    },
    {
      "tipo": "partida",
      "aerolinea": "AR",
      "vuelo": "1302",
      "st": "17/04/2020 23:00",
      "matricula": "LVFVI",
      "posicion": "14",
      "et": "",
      "at": "",
      "term": "C",
      "sector": "CPI",
      "chkFrom": "221",
      "chkTo": "240",
      "puerta": "19",
      "ruta": "MIA",
      "via": "",
      "remark": "HOR",
      "sanidad": "NO"
    },
    {
      "tipo": "partida",
      "aerolinea": "UC",
      "vuelo": "1408",
      "st": "17/04/2020 23:30",
      "matricula": "",
      "posicion": "",
      "et": "",
      "at": "",
      "term": "TCA",
      "sector": "",
      "chkFrom": "",
      "chkTo": "",
      "puerta": "",
      "ruta": "LAX",
      "via": "",
      "remark": "HOR",
      "sanidad": "NO"
    },
    {
      "tipo": "partida",
      "aerolinea": "JJ",
      "vuelo": "H24",
      "st": "17/04/2020 23:59",
      "matricula": "",
      "posicion": "",
      "et": "",
      "at": "",
      "term": "A",
      "sector": "AP",
      "chkFrom": "041",
      "chkTo": "053",
      "puerta": "",
      "ruta": "QTR",
      "via": "",
      "remark": "HOR",
      "sanidad": "NO"
    },
    {
      "tipo": "partida",
      "aerolinea": "AR",
      "vuelo": "H24N",
      "st": "17/04/2020 23:59",
      "matricula": "",
      "posicion": "",
      "et": "",
      "at": "",
      "term": "C",
      "sector": "CPI",
      "chkFrom": "209",
      "chkTo": "240",
      "puerta": "",
      "ruta": "QTR",
      "via": "",
      "remark": "HOR",
      "sanidad": "NO"
    },
    {
      "tipo": "partida",
      "aerolinea": "AR",
      "vuelo": "H24",
      "st": "17/04/2020 23:59",
      "matricula": "",
      "posicion": "",
      "et": "",
      "at": "",
      "term": "C",
      "sector": "CPI",
      "chkFrom": "221",
      "chkTo": "240",
      "puerta": "",
      "ruta": "QTR",
      "via": "",
      "remark": "HOR",
      "sanidad": "NO"
    },
    {
      "tipo": "partida",
      "aerolinea": "LA",
      "vuelo": "1148",
      "st": "18/04/2020 00:00",
      "matricula": "CCBGI",
      "posicion": "",
      "et": "",
      "at": "",
      "term": "TCA",
      "sector": "",
      "chkFrom": "",
      "chkTo": "",
      "puerta": "",
      "ruta": "MIA",
      "via": "",
      "remark": "HOR",
      "sanidad": "NO"
    },
    {
      "tipo": "partida",
      "aerolinea": "M3",
      "vuelo": "8496",
      "st": "18/04/2020 02:10",
      "matricula": "",
      "posicion": "",
      "et": "",
      "at": "",
      "term": "TCA",
      "sector": "",
      "chkFrom": "",
      "chkTo": "",
      "puerta": "",
      "ruta": "SCL",
      "via": "",
      "remark": "HOR",
      "sanidad": "NO"
    },
    {
      "tipo": "partida",
      "aerolinea": "UC",
      "vuelo": "1406",
      "st": "18/04/2020 03:30",
      "matricula": "",
      "posicion": "",
      "et": "",
      "at": "",
      "term": "TCA",
      "sector": "",
      "chkFrom": "",
      "chkTo": "",
      "puerta": "",
      "ruta": "LAX",
      "via": "",
      "remark": "HOR",
      "sanidad": "NO"
    },
    {
      "tipo": "partida",
      "aerolinea": "5X",
      "vuelo": "413",
      "st": "18/04/2020 06:05",
      "matricula": "N301UP",
      "posicion": "55",
      "et": "18/4/2020 05:30",
      "at": "",
      "term": "TCA",
      "sector": "",
      "chkFrom": "",
      "chkTo": "",
      "puerta": "",
      "ruta": "MIA",
      "via": "VCP",
      "remark": "EST",
      "sanidad": "NO"
    }
  ]
}